adobe_aam/__init__.py
adobe_aam/helpers/__init__.py
adobe_aam/helpers/headers.py
adobe_aam/helpers/simplify.py
adobe_aam/login/__init__.py
adobe_aam/login/login.py
adobe_aam/reports/__init__.py
adobe_aam/reports/reports.py
adobe_aam/segmentFolders/__init__.py
adobe_aam/segmentFolders/segmentFolders.py
adobe_aam/segments/__init__.py
adobe_aam/segments/segments.py
adobe_aam/traitFolders/__init__.py
adobe_aam/traitFolders/traitFolders.py
adobe_aam/traits/__init__.py
adobe_aam/traits/traits.py
adobe_aam-0.0.9.dist-info/LICENSE.md
adobe_aam-0.0.9.dist-info/METADATA
adobe_aam-0.0.9.dist-info/WHEEL
adobe_aam-0.0.9.dist-info/top_level.txt
adobe_aam-0.0.9.dist-info/RECORD
