Metadata-Version: 2.1
Name: adobe-aam
Version: 0.0.9
Summary: Adobe Audience Manager API Python Extension
Home-page: https://github.com/trevormccormick/adobe_aam_python/
Author: Trevor McCormick
Author-email: trevor.ryan.mccormick@gmail.com
License: UNKNOWN
Platform: UNKNOWN
Classifier: Programming Language :: Python :: 3.7
Classifier: License :: OSI Approved :: GNU General Public License v3 (GPLv3)
Requires-Dist: PyJWT (>=2.0.1)
Requires-Dist: cryptography (>=3.4.4)
Requires-Dist: requests (>=2)
Requires-Dist: pandas (>=1.1.5)
